Workbook

Sheet About
A1: Regional Growth Analysis
A2: Veda Technology | Data Analytics Track | Prepared by Sneha
A4: Objective | B4: Compare how fast each region (Central, East, South, West) grew from 2014 to 2017 and check whether the growth numbers can be trusted (period-over-period comparison, small-base effect).
A5: Dataset | B5: Superstore (superstore.csv) - 9,994 order lines, orders from 3 Jan 2014 to 30 Dec 2017, 4 regions.
A6: Period rule | B6: Calendar years (Jan-Dec) and calendar quarters. Same period length every time; quarters are compared with the SAME quarter of the previous year.
A7: Growth formula | B7: YoY % = (this period / previous period) - 1. CAGR = (2017 / 2014)^(1/3) - 1.
A8: Small-base flag | B8: A growth % is flagged SMALL BASE when the previous-year value is below the threshold (cell Small_Base_Check!B3, default 50%) of that region's own 4-year average.
A9: How the work was done | B9: SQL (SQLite) was used to build the clean year/quarter view and run the growth queries - file regional_growth_analysis.sql. Excel rebuilds the same tables with live SUMIFS formulas on the Data sheet, and the SQL_vs_Excel sheet checks that both agree.
A10: Sheets | B10: Data | Growth_Table | Quarterly_YoY | Small_Base_Check | Charts | SQL_vs_Excel | Insights
A11: Colour code | B11: Blue text = number typed in or pasted from SQL output. Black = formula. Yellow cell = assumption you can change.

Sheet Data
A1: Order ID | B1: Order Date | C1: Region | D1: State | E1: Category | F1: Sales | G1: Profit | H1: Discount | I1: Year | J1: Quarter
A2: CA-2016-152156 | B2: 42682 | C2: South | D2: Kentucky | E2: Furniture | F2: 261.96 | G2: 41.9136 | H2: 0 | I2: =YEAR(B2) -> 2016 | J2: =I2&"-Q"&ROUNDUP(MONTH(B2)/3,0) -> 2016-Q4
A3: CA-2016-152156 | B3: 42682 | C3: South | D3: Kentucky | E3: Furniture | F3: 731.94 | G3: 219.582 | H3: 0 | I3: =YEAR(B3) -> 2016 | J3: =I3&"-Q"&ROUNDUP(MONTH(B3)/3,0) -> 2016-Q4
A4: CA-2016-138688 | B4: 42533 | C4: West | D4: California | E4: Office Supplies | F4: 14.62 | G4: 6.8714 | H4: 0 | I4: =YEAR(B4) -> 2016 | J4: =I4&"-Q"&ROUNDUP(MONTH(B4)/3,0) -> 2016-Q2
A5: US-2015-108966 | B5: 42288 | C5: South | D5: Florida | E5: Furniture | F5: 957.5775 | G5: -383.031 | H5: 0.45 | I5: =YEAR(B5) -> 2015 | J5: =I5&"-Q"&ROUNDUP(MONTH(B5)/3,0) -> 2015-Q4
A6: US-2015-108966 | B6: 42288 | C6: South | D6: Florida | E6: Office Supplies | F6: 22.368 | G6: 2.5164 | H6: 0.2 | I6: =YEAR(B6) -> 2015 | J6: =I6&"-Q"&ROUNDUP(MONTH(B6)/3,0) -> 2015-Q4
A7: CA-2014-115812 | B7: 41799 | C7: West | D7: California | E7: Furniture | F7: 48.86 | G7: 14.1694 | H7: 0 | I7: =YEAR(B7) -> 2014 | J7: =I7&"-Q"&ROUNDUP(MONTH(B7)/3,0) -> 2014-Q2
A8: CA-2014-115812 | B8: 41799 | C8: West | D8: California | E8: Office Supplies | F8: 7.28 | G8: 1.9656 | H8: 0 | I8: =YEAR(B8) -> 2014 | J8: =I8&"-Q"&ROUNDUP(MONTH(B8)/3,0) -> 2014-Q2
A9: CA-2014-115812 | B9: 41799 | C9: West | D9: California | E9: Technology | F9: 907.152 | G9: 90.7152 | H9: 0.2 | I9: =YEAR(B9) -> 2014 | J9: =I9&"-Q"&ROUNDUP(MONTH(B9)/3,0) -> 2014-Q2
A10: CA-2014-115812 | B10: 41799 | C10: West | D10: California | E10: Office Supplies | F10: 18.504 | G10: 5.7825 | H10: 0.2 | I10: =YEAR(B10) -> 2014 | J10: =I10&"-Q"&ROUNDUP(MONTH(B10)/3,0) -> 2014-Q2
A11: CA-2014-115812 | B11: 41799 | C11: West | D11: California | E11: Office Supplies | F11: 114.9 | G11: 34.47 | H11: 0 | I11: =YEAR(B11) -> 2014 | J11: =I11&"-Q"&ROUNDUP(MONTH(B11)/3,0) -> 2014-Q2
A12: CA-2014-115812 | B12: 41799 | C12: West | D12: California | E12: Furniture | F12: 1706.184 | G12: 85.3092 | H12: 0.2 | I12: =YEAR(B12) -> 2014 | J12: =I12&"-Q"&ROUNDUP(MONTH(B12)/3,0) -> 2014-Q2
A13: CA-2014-115812 | B13: 41799 | C13: West | D13: California | E13: Technology | F13: 911.424 | G13: 68.3568 | H13: 0.2 | I13: =YEAR(B13) -> 2014 | J13: =I13&"-Q"&ROUNDUP(MONTH(B13)/3,0) -> 2014-Q2
... A9995: CA-2017-119914 | B9995: 42859 | C9995: West | D9995: California | E9995: Office Supplies | F9995: 243.16 | G9995: 72.948 | H9995: 0 | I9995: =YEAR(B9995) -> 2017 | J9995: =I9995&"-Q"&ROUNDUP(MONTH(B9995)/3,0) -> 2017-Q2

Sheet Growth_Table
A1: Regional Growth Table
A2: All figures are live SUMIFS on the Data sheet. Years are calendar years.
A3: 1. Sales by region (USD)
A4: Region | B4: 2014 | C4: 2015 | D4: 2016 | E4: 2017 | F4: CAGR 2014-17 | G4: Gain 2014-17 | H4: Share of company gain
A5: Central | B5: =SUMIFS(Data!$F$2:$F$9995,Data!$C$2:$C$9995,$A5,Data!$I$2:$I$9995,B$4) -> 103838.16 | C5: =SUMIFS(Data!$F$2:$F$9995,Data!$C$2:$C$9995,$A5,Data!$I$2:$I$9995,C$4) -> 102874.22 | D5: =SUMIFS(Data!$F$2:$F$9995,Data!$C$2:$C$9995,$A5,Data!$I$2:$I$9995,D$4) -> 147429.38 | E5: =SUMIFS(Data!$F$2:$F$9995,Data!$C$2:$C$9995,$A5,Data!$I$2:$I$9995,E$4) -> 147098.13 | F5: =(E5/B5)^(1/(E$4-B$4))-1 -> 0.12309557 | G5: =E5-B5 -> 43259.964 | H5: =G5/G$9 -> 0.17375729
A6: East | B6: =SUMIFS(Data!$F$2:$F$9995,Data!$C$2:$C$9995,$A6,Data!$I$2:$I$9995,B$4) -> 128680.46 | C6: =SUMIFS(Data!$F$2:$F$9995,Data!$C$2:$C$9995,$A6,Data!$I$2:$I$9995,C$4) -> 156332.06 | D6: =SUMIFS(Data!$F$2:$F$9995,Data!$C$2:$C$9995,$A6,Data!$I$2:$I$9995,D$4) -> 180685.82 | E6: =SUMIFS(Data!$F$2:$F$9995,Data!$C$2:$C$9995,$A6,Data!$I$2:$I$9995,E$4) -> 213082.9 | F6: =(E6/B6)^(1/(E$4-B$4))-1 -> 0.18307426 | G6: =E6-B6 -> 84402.447 | H6: =G6/G$9 -> 0.33900955
A7: South | B7: =SUMIFS(Data!$F$2:$F$9995,Data!$C$2:$C$9995,$A7,Data!$I$2:$I$9995,B$4) -> 103845.84 | C7: =SUMIFS(Data!$F$2:$F$9995,Data!$C$2:$C$9995,$A7,Data!$I$2:$I$9995,C$4) -> 71359.981 | D7: =SUMIFS(Data!$F$2:$F$9995,Data!$C$2:$C$9995,$A7,Data!$I$2:$I$9995,D$4) -> 93610.223 | E7: =SUMIFS(Data!$F$2:$F$9995,Data!$C$2:$C$9995,$A7,Data!$I$2:$I$9995,E$4) -> 122905.86 | F7: =(E7/B7)^(1/(E$4-B$4))-1 -> 0.057777896 | G7: =E7-B7 -> 19060.014 | H7: =G7/G$9 -> 0.076556154
A8: West | B8: =SUMIFS(Data!$F$2:$F$9995,Data!$C$2:$C$9995,$A8,Data!$I$2:$I$9995,B$4) -> 147883.03 | C8: =SUMIFS(Data!$F$2:$F$9995,Data!$C$2:$C$9995,$A8,Data!$I$2:$I$9995,C$4) -> 139966.25 | D8: =SUMIFS(Data!$F$2:$F$9995,Data!$C$2:$C$9995,$A8,Data!$I$2:$I$9995,D$4) -> 187480.18 | E8: =SUMIFS(Data!$F$2:$F$9995,Data!$C$2:$C$9995,$A8,Data!$I$2:$I$9995,E$4) -> 250128.37 | F8: =(E8/B8)^(1/(E$4-B$4))-1 -> 0.19146567 | G8: =E8-B8 -> 102245.33 | H8: =G8/G$9 -> 0.410677
A9: Total | B9: =SUM(B5:B8) -> 484247.5 | C9: =SUM(C5:C8) -> 470532.51 | D9: =SUM(D5:D8) -> 609205.6 | E9: =SUM(E5:E8) -> 733215.26 | F9: =(E9/B9)^(1/(E$4-B$4))-1 -> 0.14829825 | G9: =E9-B9 -> 248967.76 | H9: =G9/G$9 -> 1
A11: 2. Sales growth, year over year (%)
A12: Region | B12: 2014 | C12: 2015 | D12: 2016 | E12: 2017
A13: Central | B13: n/a | C13: =IFERROR(C5/B5-1,"n/a") -> -0.0092831244 | D13: =IFERROR(D5/C5-1,"n/a") -> 0.43310319 | E13: =IFERROR(E5/D5-1,"n/a") -> -0.0022468236
A14: East | B14: n/a | C14: =IFERROR(C6/B6-1,"n/a") -> 0.21488578 | D14: =IFERROR(D6/C6-1,"n/a") -> 0.15578228 | E14: =IFERROR(E6/D6-1,"n/a") -> 0.17930063
A15: South | B15: n/a | C15: =IFERROR(C7/B7-1,"n/a") -> -0.31282776 | D15: =IFERROR(D7/C7-1,"n/a") -> 0.31180282 | E15: =IFERROR(E7/D7-1,"n/a") -> 0.31295336
A16: West | B16: n/a | C16: =IFERROR(C8/B8-1,"n/a") -> -0.053534089 | D16: =IFERROR(D8/C8-1,"n/a") -> 0.33946703 | E16: =IFERROR(E8/D8-1,"n/a") -> 0.334159
A17: Total | B17: n/a | C17: =IFERROR(C9/B9-1,"n/a") -> -0.028322271 | D17: =IFERROR(D9/C9-1,"n/a") -> 0.29471521 | E17: =IFERROR(E9/D9-1,"n/a") -> 0.20355962
A19: 3. Profit by region (USD)
A20: Region | B20: 2014 | C20: 2015 | D20: 2016 | E20: 2017 | F20: Total 2014-17
A21: Central | B21: =SUMIFS(Data!$G$2:$G$9995,Data!$C$2:$C$9995,$A21,Data!$I$2:$I$9995,B$20) -> 539.5534 | C21: =SUMIFS(Data!$G$2:$G$9995,Data!$C$2:$C$9995,$A21,Data!$I$2:$I$9995,C$20) -> 11716.802 | D21: =SUMIFS(Data!$G$2:$G$9995,Data!$C$2:$C$9995,$A21,Data!$I$2:$I$9995,D$20) -> 19899.163 | E21: =SUMIFS(Data!$G$2:$G$9995,Data!$C$2:$C$9995,$A21,Data!$I$2:$I$9995,E$20) -> 7550.8442 | F21: =SUM(B21:E21) -> 39706.363
A22: East | B22: =SUMIFS(Data!$G$2:$G$9995,Data!$C$2:$C$9995,$A22,Data!$I$2:$I$9995,B$20) -> 17059.609 | C22: =SUMIFS(Data!$G$2:$G$9995,Data!$C$2:$C$9995,$A22,Data!$I$2:$I$9995,C$20) -> 21091.013 | D22: =SUMIFS(Data!$G$2:$G$9995,Data!$C$2:$C$9995,$A22,Data!$I$2:$I$9995,D$20) -> 20141.596 | E22: =SUMIFS(Data!$G$2:$G$9995,Data!$C$2:$C$9995,$A22,Data!$I$2:$I$9995,E$20) -> 33230.561 | F22: =SUM(B22:E22) -> 91522.78
A23: South | B23: =SUMIFS(Data!$G$2:$G$9995,Data!$C$2:$C$9995,$A23,Data!$I$2:$I$9995,B$20) -> 11879.12 | C23: =SUMIFS(Data!$G$2:$G$9995,Data!$C$2:$C$9995,$A23,Data!$I$2:$I$9995,C$20) -> 8318.594 | D23: =SUMIFS(Data!$G$2:$G$9995,Data!$C$2:$C$9995,$A23,Data!$I$2:$I$9995,D$20) -> 17702.808 | E23: =SUMIFS(Data!$G$2:$G$9995,Data!$C$2:$C$9995,$A23,Data!$I$2:$I$9995,E$20) -> 8848.9079 | F23: =SUM(B23:E23) -> 46749.43
A24: West | B24: =SUMIFS(Data!$G$2:$G$9995,Data!$C$2:$C$9995,$A24,Data!$I$2:$I$9995,B$20) -> 20065.691 | C24: =SUMIFS(Data!$G$2:$G$9995,Data!$C$2:$C$9995,$A24,Data!$I$2:$I$9995,C$20) -> 20492.195 | D24: =SUMIFS(Data!$G$2:$G$9995,Data!$C$2:$C$9995,$A24,Data!$I$2:$I$9995,D$20) -> 24051.607 | E24: =SUMIFS(Data!$G$2:$G$9995,Data!$C$2:$C$9995,$A24,Data!$I$2:$I$9995,E$20) -> 43808.956 | F24: =SUM(B24:E24) -> 108418.45
A25: Total | B25: =SUM(B21:B24) -> 49543.974 | C25: =SUM(C21:C24) -> 61618.604 | D25: =SUM(D21:D24) -> 81795.174 | E25: =SUM(E21:E24) -> 93439.27 | F25: =SUM(B25:E25) -> 286397.02
A27: 4. Profit growth, year over year (%) - read together with the Small_Base_Check sheet
A28: Region | B28: 2014 | C28: 2015 | D28: 2016 | E28: 2017
A29: Central | B29: n/a | C29: =IFERROR(C21/B21-1,"n/a") -> 20.715741 | D29: =IFERROR(D21/C21-1,"n/a") -> 0.69834422 | E29: =IFERROR(E21/D21-1,"n/a") -> -0.62054463
A30: East | B30: n/a | C30: =IFERROR(C22/B22-1,"n/a") -> 0.23631277 | D30: =IFERROR(D22/C22-1,"n/a") -> -0.045015235 | E30: =IFERROR(E22/D22-1,"n/a") -> 0.64984747
A31: South | B31: n/a | C31: =IFERROR(C23/B23-1,"n/a") -> -0.29972978 | D31: =IFERROR(D23/C23-1,"n/a") -> 1.128101 | E31: =IFERROR(E23/D23-1,"n/a") -> -0.50014101
A32: West | B32: n/a | C32: =IFERROR(C24/B24-1,"n/a") -> 0.02125536 | D32: =IFERROR(D24/C24-1,"n/a") -> 0.173696 | E32: =IFERROR(E24/D24-1,"n/a") -> 0.82145652
A33: Total | B33: n/a | C33: =IFERROR(C25/B25-1,"n/a") -> 0.2437154 | D33: =IFERROR(D25/C25-1,"n/a") -> 0.32744284 | E33: =IFERROR(E25/D25-1,"n/a") -> 0.14235675
A35: 5. Profit margin (profit / sales)
A36: Region | B36: 2014 | C36: 2015 | D36: 2016 | E36: 2017
A37: Central | B37: =IFERROR(B21/B5,0) -> 0.0051960992 | C37: =IFERROR(C21/C5,0) -> 0.11389444 | D37: =IFERROR(D21/D5,0) -> 0.13497421 | E37: =IFERROR(E21/E5,0) -> 0.051332021
A38: East | B38: =IFERROR(B22/B6,0) -> 0.13257343 | C38: =IFERROR(C22/C6,0) -> 0.13491163 | D38: =IFERROR(D22/D6,0) -> 0.11147303 | E38: =IFERROR(E22/E6,0) -> 0.15595133
A39: South | B39: =IFERROR(B23/B7,0) -> 0.11439187 | C39: =IFERROR(C23/C7,0) -> 0.11657226 | D39: =IFERROR(D23/D7,0) -> 0.18911191 | E39: =IFERROR(E23/E7,0) -> 0.071997447
A40: West | B40: =IFERROR(B24/B8,0) -> 0.13568623 | C40: =IFERROR(C24/C8,0) -> 0.14640811 | D40: =IFERROR(D24/D8,0) -> 0.1282888 | E40: =IFERROR(E24/E8,0) -> 0.17514589
A41: Total | B41: =IFERROR(B25/B9,0) -> 0.10231126 | C41: =IFERROR(C25/C9,0) -> 0.13095504 | D41: =IFERROR(D25/D9,0) -> 0.1342653 | E41: =IFERROR(E25/E9,0) -> 0.12743771

Sheet Quarterly_YoY
A1: Quarterly Sales and Same-Quarter Growth
A2: Right block compares each quarter with the same quarter one year earlier, so the Q4 festive spike does not look like growth.
A3: Quarter | B3: Central | C3: East | D3: South | E3: West | F3: Total | H3: Quarter | I3: Central | J3: East | K3: South | L3: West | M3: Total
A4: 2014-Q1 | B4: =SUMIFS(Data!$F$2:$F$9995,Data!$C$2:$C$9995,B$3,Data!$J$2:$J$9995,$A4) -> 8600.682 | C4: =SUMIFS(Data!$F$2:$F$9995,Data!$C$2:$C$9995,C$3,Data!$J$2:$J$9995,$A4) -> 6579.338 | D4: =SUMIFS(Data!$F$2:$F$9995,Data!$C$2:$C$9995,D$3,Data!$J$2:$J$9995,$A4) -> 44262.199 | E4: =SUMIFS(Data!$F$2:$F$9995,Data!$C$2:$C$9995,E$3,Data!$J$2:$J$9995,$A4) -> 15005.577 | F4: =SUM(B4:E4) -> 74447.796 | H4: 2014-Q1 | I4: n/a | J4: n/a | K4: n/a | L4: n/a | M4: n/a
A5: 2014-Q2 | B5: =SUMIFS(Data!$F$2:$F$9995,Data!$C$2:$C$9995,B$3,Data!$J$2:$J$9995,$A5) -> 17407.145 | C5: =SUMIFS(Data!$F$2:$F$9995,Data!$C$2:$C$9995,C$3,Data!$J$2:$J$9995,$A5) -> 21064.165 | D5: =SUMIFS(Data!$F$2:$F$9995,Data!$C$2:$C$9995,D$3,Data!$J$2:$J$9995,$A5) -> 22524.103 | E5: =SUMIFS(Data!$F$2:$F$9995,Data!$C$2:$C$9995,E$3,Data!$J$2:$J$9995,$A5) -> 25543.347 | F5: =SUM(B5:E5) -> 86538.76 | H5: 2014-Q2 | I5: n/a | J5: n/a | K5: n/a | L5: n/a | M5: n/a
A6: 2014-Q3 | B6: =SUMIFS(Data!$F$2:$F$9995,Data!$C$2:$C$9995,B$3,Data!$J$2:$J$9995,$A6) -> 44171.447 | C6: =SUMIFS(Data!$F$2:$F$9995,Data!$C$2:$C$9995,C$3,Data!$J$2:$J$9995,$A6) -> 33443.383 | D6: =SUMIFS(Data!$F$2:$F$9995,Data!$C$2:$C$9995,D$3,Data!$J$2:$J$9995,$A6) -> 16061.061 | E6: =SUMIFS(Data!$F$2:$F$9995,Data!$C$2:$C$9995,E$3,Data!$J$2:$J$9995,$A6) -> 49957.321 | F6: =SUM(B6:E6) -> 143633.21 | H6: 2014-Q3 | I6: n/a | J6: n/a | K6: n/a | L6: n/a | M6: n/a
A7: 2014-Q4 | B7: =SUMIFS(Data!$F$2:$F$9995,Data!$C$2:$C$9995,B$3,Data!$J$2:$J$9995,$A7) -> 33658.891 | C7: =SUMIFS(Data!$F$2:$F$9995,Data!$C$2:$C$9995,C$3,Data!$J$2:$J$9995,$A7) -> 67593.571 | D7: =SUMIFS(Data!$F$2:$F$9995,Data!$C$2:$C$9995,D$3,Data!$J$2:$J$9995,$A7) -> 20998.48 | E7: =SUMIFS(Data!$F$2:$F$9995,Data!$C$2:$C$9995,E$3,Data!$J$2:$J$9995,$A7) -> 57376.788 | F7: =SUM(B7:E7) -> 179627.73 | H7: 2014-Q4 | I7: n/a | J7: n/a | K7: n/a | L7: n/a | M7: n/a
A8: 2015-Q1 | B8: =SUMIFS(Data!$F$2:$F$9995,Data!$C$2:$C$9995,B$3,Data!$J$2:$J$9995,$A8) -> 11768.366 | C8: =SUMIFS(Data!$F$2:$F$9995,Data!$C$2:$C$9995,C$3,Data!$J$2:$J$9995,$A8) -> 17145.868 | D8: =SUMIFS(Data!$F$2:$F$9995,Data!$C$2:$C$9995,D$3,Data!$J$2:$J$9995,$A8) -> 16444.443 | E8: =SUMIFS(Data!$F$2:$F$9995,Data!$C$2:$C$9995,E$3,Data!$J$2:$J$9995,$A8) -> 23493.062 | F8: =SUM(B8:E8) -> 68851.739 | H8: 2015-Q1 | I8: =IFERROR(B8/B4-1,"n/a") -> 0.36830609 | J8: =IFERROR(C8/C4-1,"n/a") -> 1.6060172 | K8: =IFERROR(D8/D4-1,"n/a") -> -0.62847659 | L8: =IFERROR(E8/E4-1,"n/a") -> 0.56562204 | M8: =IFERROR(F8/F4-1,"n/a") -> -0.075167536
A9: 2015-Q2 | B9: =SUMIFS(Data!$F$2:$F$9995,Data!$C$2:$C$9995,B$3,Data!$J$2:$J$9995,$A9) -> 23979.145 | C9: =SUMIFS(Data!$F$2:$F$9995,Data!$C$2:$C$9995,C$3,Data!$J$2:$J$9995,$A9) -> 22703.208 | D9: =SUMIFS(Data!$F$2:$F$9995,Data!$C$2:$C$9995,D$3,Data!$J$2:$J$9995,$A9) -> 16254.204 | E9: =SUMIFS(Data!$F$2:$F$9995,Data!$C$2:$C$9995,E$3,Data!$J$2:$J$9995,$A9) -> 26187.629 | F9: =SUM(B9:E9) -> 89124.187 | H9: 2015-Q2 | I9: =IFERROR(B9/B5-1,"n/a") -> 0.37754615 | J9: =IFERROR(C9/C5-1,"n/a") -> 0.077811914 | K9: =IFERROR(D9/D5-1,"n/a") -> -0.27836396 | L9: =IFERROR(E9/E5-1,"n/a") -> 0.025223104 | M9: =IFERROR(F9/F5-1,"n/a") -> 0.029875947
A10: 2015-Q3 | B10: =SUMIFS(Data!$F$2:$F$9995,Data!$C$2:$C$9995,B$3,Data!$J$2:$J$9995,$A10) -> 24485.538 | C10: =SUMIFS(Data!$F$2:$F$9995,Data!$C$2:$C$9995,C$3,Data!$J$2:$J$9995,$A10) -> 50777.423 | D10: =SUMIFS(Data!$F$2:$F$9995,Data!$C$2:$C$9995,D$3,Data!$J$2:$J$9995,$A10) -> 21459.505 | E10: =SUMIFS(Data!$F$2:$F$9995,Data!$C$2:$C$9995,E$3,Data!$J$2:$J$9995,$A10) -> 33537.109 | F10: =SUM(B10:E10) -> 130259.58 | H10: 2015-Q3 | I10: =IFERROR(B10/B6-1,"n/a") -> -0.44567045 | J10: =IFERROR(C10/C6-1,"n/a") -> 0.51831 | K10: =IFERROR(D10/D6-1,"n/a") -> 0.33611997 | L10: =IFERROR(E10/E6-1,"n/a") -> -0.3286848 | M10: =IFERROR(F10/F6-1,"n/a") -> -0.093109643
A11: 2015-Q4 | B11: =SUMIFS(Data!$F$2:$F$9995,Data!$C$2:$C$9995,B$3,Data!$J$2:$J$9995,$A11) -> 42641.173 | C11: =SUMIFS(Data!$F$2:$F$9995,Data!$C$2:$C$9995,C$3,Data!$J$2:$J$9995,$A11) -> 65705.558 | D11: =SUMIFS(Data!$F$2:$F$9995,Data!$C$2:$C$9995,D$3,Data!$J$2:$J$9995,$A11) -> 17201.828 | E11: =SUMIFS(Data!$F$2:$F$9995,Data!$C$2:$C$9995,E$3,Data!$J$2:$J$9995,$A11) -> 56748.449 | F11: =SUM(B11:E11) -> 182297.01 | H11: 2015-Q4 | I11: =IFERROR(B11/B7-1,"n/a") -> 0.26686209 | J11: =IFERROR(C11/C7-1,"n/a") -> -0.027931843 | K11: =IFERROR(D11/D7-1,"n/a") -> -0.18080604 | L11: =IFERROR(E11/E7-1,"n/a") -> -0.010951101 | M11: =IFERROR(F11/F7-1,"n/a") -> 0.014860055
A12: 2016-Q1 | B12: =SUMIFS(Data!$F$2:$F$9995,Data!$C$2:$C$9995,B$3,Data!$J$2:$J$9995,$A12) -> 20211.697 | C12: =SUMIFS(Data!$F$2:$F$9995,Data!$C$2:$C$9995,C$3,Data!$J$2:$J$9995,$A12) -> 24774.765 | D12: =SUMIFS(Data!$F$2:$F$9995,Data!$C$2:$C$9995,D$3,Data!$J$2:$J$9995,$A12) -> 23933.704 | E12: =SUMIFS(Data!$F$2:$F$9995,Data!$C$2:$C$9995,E$3,Data!$J$2:$J$9995,$A12) -> 24317.015 | F12: =SUM(B12:E12) -> 93237.181 | H12: 2016-Q1 | I12: =IFERROR(B12/B8-1,"n/a") -> 0.71745998 | J12: =IFERROR(C12/C8-1,"n/a") -> 0.44494085 | K12: =IFERROR(D12/D8-1,"n/a") -> 0.45542807 | L12: =IFERROR(E12/E8-1,"n/a") -> 0.035072184 | M12: =IFERROR(F12/F8-1,"n/a") -> 0.35417323
A13: 2016-Q2 | B13: =SUMIFS(Data!$F$2:$F$9995,Data!$C$2:$C$9995,B$3,Data!$J$2:$J$9995,$A13) -> 25759.465 | C13: =SUMIFS(Data!$F$2:$F$9995,Data!$C$2:$C$9995,C$3,Data!$J$2:$J$9995,$A13) -> 52166.657 | D13: =SUMIFS(Data!$F$2:$F$9995,Data!$C$2:$C$9995,D$3,Data!$J$2:$J$9995,$A13) -> 18381.828 | E13: =SUMIFS(Data!$F$2:$F$9995,Data!$C$2:$C$9995,E$3,Data!$J$2:$J$9995,$A13) -> 39774.351 | F13: =SUM(B13:E13) -> 136082.3 | H13: 2016-Q2 | I13: =IFERROR(B13/B9-1,"n/a") -> 0.074244515 | J13: =IFERROR(C13/C9-1,"n/a") -> 1.2977659 | K13: =IFERROR(D13/D9-1,"n/a") -> 0.13089681 | L13: =IFERROR(E13/E9-1,"n/a") -> 0.51882212 | M13: =IFERROR(F13/F9-1,"n/a") -> 0.52688407
A14: 2016-Q3 | B14: =SUMIFS(Data!$F$2:$F$9995,Data!$C$2:$C$9995,B$3,Data!$J$2:$J$9995,$A14) -> 33380.224 | C14: =SUMIFS(Data!$F$2:$F$9995,Data!$C$2:$C$9995,C$3,Data!$J$2:$J$9995,$A14) -> 38051.646 | D14: =SUMIFS(Data!$F$2:$F$9995,Data!$C$2:$C$9995,D$3,Data!$J$2:$J$9995,$A14) -> 21635.88 | E14: =SUMIFS(Data!$F$2:$F$9995,Data!$C$2:$C$9995,E$3,Data!$J$2:$J$9995,$A14) -> 50719.611 | F14: =SUM(B14:E14) -> 143787.36 | H14: 2016-Q3 | I14: =IFERROR(B14/B10-1,"n/a") -> 0.36326283 | J14: =IFERROR(C14/C10-1,"n/a") -> -0.2506188 | K14: =IFERROR(D14/D10-1,"n/a") -> 0.008218992 | L14: =IFERROR(E14/E10-1,"n/a") -> 0.51234298 | M14: =IFERROR(F14/F10-1,"n/a") -> 0.10385253
A15: 2016-Q4 | B15: =SUMIFS(Data!$F$2:$F$9995,Data!$C$2:$C$9995,B$3,Data!$J$2:$J$9995,$A15) -> 68077.99 | C15: =SUMIFS(Data!$F$2:$F$9995,Data!$C$2:$C$9995,C$3,Data!$J$2:$J$9995,$A15) -> 65692.754 | D15: =SUMIFS(Data!$F$2:$F$9995,Data!$C$2:$C$9995,D$3,Data!$J$2:$J$9995,$A15) -> 29658.811 | E15: =SUMIFS(Data!$F$2:$F$9995,Data!$C$2:$C$9995,E$3,Data!$J$2:$J$9995,$A15) -> 72669.199 | F15: =SUM(B15:E15) -> 236098.75 | H15: 2016-Q4 | I15: =IFERROR(B15/B11-1,"n/a") -> 0.59653182 | J15: =IFERROR(C15/C11-1,"n/a") -> -0.00019486936 | K15: =IFERROR(D15/D11-1,"n/a") -> 0.72416623 | L15: =IFERROR(E15/E11-1,"n/a") -> 0.28054952 | M15: =IFERROR(F15/F11-1,"n/a") -> 0.29513236
A16: 2017-Q1 | B16: =SUMIFS(Data!$F$2:$F$9995,Data!$C$2:$C$9995,B$3,Data!$J$2:$J$9995,$A16) -> 40530.057 | C16: =SUMIFS(Data!$F$2:$F$9995,Data!$C$2:$C$9995,C$3,Data!$J$2:$J$9995,$A16) -> 18051.762 | D16: =SUMIFS(Data!$F$2:$F$9995,Data!$C$2:$C$9995,D$3,Data!$J$2:$J$9995,$A16) -> 13642.182 | E16: =SUMIFS(Data!$F$2:$F$9995,Data!$C$2:$C$9995,E$3,Data!$J$2:$J$9995,$A16) -> 50920.859 | F16: =SUM(B16:E16) -> 123144.86 | H16: 2017-Q1 | I16: =IFERROR(B16/B12-1,"n/a") -> 1.0052773 | J16: =IFERROR(C16/C12-1,"n/a") -> -0.27136496 | K16: =IFERROR(D16/D12-1,"n/a") -> -0.43000122 | L16: =IFERROR(E16/E12-1,"n/a") -> 1.0940423 | M16: =IFERROR(F16/F12-1,"n/a") -> 0.32076988
A17: 2017-Q2 | B17: =SUMIFS(Data!$F$2:$F$9995,Data!$C$2:$C$9995,B$3,Data!$J$2:$J$9995,$A17) -> 27938.739 | C17: =SUMIFS(Data!$F$2:$F$9995,Data!$C$2:$C$9995,C$3,Data!$J$2:$J$9995,$A17) -> 31511.5 | D17: =SUMIFS(Data!$F$2:$F$9995,Data!$C$2:$C$9995,D$3,Data!$J$2:$J$9995,$A17) -> 29325.414 | E17: =SUMIFS(Data!$F$2:$F$9995,Data!$C$2:$C$9995,E$3,Data!$J$2:$J$9995,$A17) -> 44988.719 | F17: =SUM(B17:E17) -> 133764.37 | H17: 2017-Q2 | I17: =IFERROR(B17/B13-1,"n/a") -> 0.084600903 | J17: =IFERROR(C17/C13-1,"n/a") -> -0.39594557 | K17: =IFERROR(D17/D13-1,"n/a") -> 0.59534811 | L17: =IFERROR(E17/E13-1,"n/a") -> 0.13109875 | M17: =IFERROR(F17/F13-1,"n/a") -> -0.017033288
A18: 2017-Q3 | B18: =SUMIFS(Data!$F$2:$F$9995,Data!$C$2:$C$9995,B$3,Data!$J$2:$J$9995,$A18) -> 32468.947 | C18: =SUMIFS(Data!$F$2:$F$9995,Data!$C$2:$C$9995,C$3,Data!$J$2:$J$9995,$A18) -> 65496.387 | D18: =SUMIFS(Data!$F$2:$F$9995,Data!$C$2:$C$9995,D$3,Data!$J$2:$J$9995,$A18) -> 23874.152 | E18: =SUMIFS(Data!$F$2:$F$9995,Data!$C$2:$C$9995,E$3,Data!$J$2:$J$9995,$A18) -> 74412.47 | F18: =SUM(B18:E18) -> 196251.96 | H18: 2017-Q3 | I18: =IFERROR(B18/B14-1,"n/a") -> -0.027299913 | J18: =IFERROR(C18/C14-1,"n/a") -> 0.72124977 | K18: =IFERROR(D18/D14-1,"n/a") -> 0.10345183 | L18: =IFERROR(E18/E14-1,"n/a") -> 0.46713407 | M18: =IFERROR(F18/F14-1,"n/a") -> 0.36487625
A19: 2017-Q4 | B19: =SUMIFS(Data!$F$2:$F$9995,Data!$C$2:$C$9995,B$3,Data!$J$2:$J$9995,$A19) -> 46160.385 | C19: =SUMIFS(Data!$F$2:$F$9995,Data!$C$2:$C$9995,C$3,Data!$J$2:$J$9995,$A19) -> 98023.255 | D19: =SUMIFS(Data!$F$2:$F$9995,Data!$C$2:$C$9995,D$3,Data!$J$2:$J$9995,$A19) -> 56064.109 | E19: =SUMIFS(Data!$F$2:$F$9995,Data!$C$2:$C$9995,E$3,Data!$J$2:$J$9995,$A19) -> 79806.318 | F19: =SUM(B19:E19) -> 280054.07 | H19: 2017-Q4 | I19: =IFERROR(B19/B15-1,"n/a") -> -0.32194847 | J19: =IFERROR(C19/C15-1,"n/a") -> 0.49214714 | K19: =IFERROR(D19/D15-1,"n/a") -> 0.89030197 | L19: =IFERROR(E19/E15-1,"n/a") -> 0.098213811 | M19: =IFERROR(F19/F15-1,"n/a") -> 0.18617342
A21: Sequential check (why Q-on-Q misleads):
A22: Central Q3-2016 to Q4-2016 | D22: =B15/B14-1 -> 1.0394707 | E22: looks like doubling - but mostly seasonality
A23: Central Q4-2016 vs Q4-2015 (same quarter) | D23: =B15/B11-1 -> 0.59653182 | E23: the real year-on-year growth

Sheet Small_Base_Check
A1: Small-Base Effect Check (profit growth)
A2: Big percentages on a tiny base are not big wins. Compare the % with the dollar change.
A3: Flag threshold (base below this share of region 4-yr average): | D3: 0.5
A5: Region | B5: Year | C5: Base (previous-yr profit) | D5: Profit | E5: Change ($) | F5: Growth (%) | G5: Region 4-yr avg profit | H5: Base / avg | I5: Flag
A6: Central | B6: 2015 | C6: =Growth_Table!B21 -> 539.5534 | D6: =Growth_Table!C21 -> 11716.802 | E6: =D6-C6 -> 11177.249 | F6: =IFERROR(D6/C6-1,"n/a") -> 20.715741 | G6: =AVERAGE(Growth_Table!B21:E21) -> 9926.5906 | H6: =C6/G6 -> 0.054354352 | I6: =IF(C6<$D$3*G6,"SMALL BASE","ok") -> SMALL BASE
A7: Central | B7: 2016 | C7: =Growth_Table!C21 -> 11716.802 | D7: =Growth_Table!D21 -> 19899.163 | E7: =D7-C7 -> 8182.3609 | F7: =IFERROR(D7/C7-1,"n/a") -> 0.69834422 | G7: =AVERAGE(Growth_Table!B21:E21) -> 9926.5906 | H7: =C7/G7 -> 1.180345 | I7: =IF(C7<$D$3*G7,"SMALL BASE","ok") -> ok
A8: Central | B8: 2017 | C8: =Growth_Table!D21 -> 19899.163 | D8: =Growth_Table!E21 -> 7550.8442 | E8: =D8-C8 -> -12348.319 | F8: =IFERROR(D8/C8-1,"n/a") -> -0.62054463 | G8: =AVERAGE(Growth_Table!B21:E21) -> 9926.5906 | H8: =C8/G8 -> 2.0046322 | I8: =IF(C8<$D$3*G8,"SMALL BASE","ok") -> ok
A9: East | B9: 2015 | C9: =Growth_Table!B22 -> 17059.609 | D9: =Growth_Table!C22 -> 21091.013 | E9: =D9-C9 -> 4031.4035 | F9: =IFERROR(D9/C9-1,"n/a") -> 0.23631277 | G9: =AVERAGE(Growth_Table!B22:E22) -> 22880.695 | H9: =C9/G9 -> 0.74558966 | I9: =IF(C9<$D$3*G9,"SMALL BASE","ok") -> ok
A10: East | B10: 2016 | C10: =Growth_Table!C22 -> 21091.013 | D10: =Growth_Table!D22 -> 20141.596 | E10: =D10-C10 -> -949.4169 | F10: =IFERROR(D10/C10-1,"n/a") -> -0.045015235 | G10: =AVERAGE(Growth_Table!B22:E22) -> 22880.695 | H10: =C10/G10 -> 0.92178201 | I10: =IF(C10<$D$3*G10,"SMALL BASE","ok") -> ok
A11: East | B11: 2017 | C11: =Growth_Table!D22 -> 20141.596 | D11: =Growth_Table!E22 -> 33230.561 | E11: =D11-C11 -> 13088.965 | F11: =IFERROR(D11/C11-1,"n/a") -> 0.64984747 | G11: =AVERAGE(Growth_Table!B22:E22) -> 22880.695 | H11: =C11/G11 -> 0.88028778 | I11: =IF(C11<$D$3*G11,"SMALL BASE","ok") -> ok
A12: South | B12: 2015 | C12: =Growth_Table!B23 -> 11879.12 | D12: =Growth_Table!C23 -> 8318.594 | E12: =D12-C12 -> -3560.526 | F12: =IFERROR(D12/C12-1,"n/a") -> -0.29972978 | G12: =AVERAGE(Growth_Table!B23:E23) -> 11687.358 | H12: =C12/G12 -> 1.0164077 | I12: =IF(C12<$D$3*G12,"SMALL BASE","ok") -> ok
A13: South | B13: 2016 | C13: =Growth_Table!C23 -> 8318.594 | D13: =Growth_Table!D23 -> 17702.808 | E13: =D13-C13 -> 9384.2144 | F13: =IFERROR(D13/C13-1,"n/a") -> 1.128101 | G13: =AVERAGE(Growth_Table!B23:E23) -> 11687.358 | H13: =C13/G13 -> 0.71176003 | I13: =IF(C13<$D$3*G13,"SMALL BASE","ok") -> ok
A14: South | B14: 2017 | C14: =Growth_Table!D23 -> 17702.808 | D14: =Growth_Table!E23 -> 8848.9079 | E14: =D14-C14 -> -8853.9005 | F14: =IFERROR(D14/C14-1,"n/a") -> -0.50014101 | G14: =AVERAGE(Growth_Table!B23:E23) -> 11687.358 | H14: =C14/G14 -> 1.5146973 | I14: =IF(C14<$D$3*G14,"SMALL BASE","ok") -> ok
A15: West | B15: 2015 | C15: =Growth_Table!B24 -> 20065.691 | D15: =Growth_Table!C24 -> 20492.195 | E15: =D15-C15 -> 426.5035 | F15: =IFERROR(D15/C15-1,"n/a") -> 0.02125536 | G15: =AVERAGE(Growth_Table!B24:E24) -> 27104.612 | H15: =C15/G15 -> 0.74030541 | I15: =IF(C15<$D$3*G15,"SMALL BASE","ok") -> ok
A16: West | B16: 2016 | C16: =Growth_Table!C24 -> 20492.195 | D16: =Growth_Table!D24 -> 24051.607 | E16: =D16-C16 -> 3559.4122 | F16: =IFERROR(D16/C16-1,"n/a") -> 0.173696 | G16: =AVERAGE(Growth_Table!B24:E24) -> 27104.612 | H16: =C16/G16 -> 0.75604087 | I16: =IF(C16<$D$3*G16,"SMALL BASE","ok") -> ok
A17: West | B17: 2017 | C17: =Growth_Table!D24 -> 24051.607 | D17: =Growth_Table!E24 -> 43808.956 | E17: =D17-C17 -> 19757.349 | F17: =IFERROR(D17/C17-1,"n/a") -> 0.82145652 | G17: =AVERAGE(Growth_Table!B24:E24) -> 27104.612 | H17: =C17/G17 -> 0.88736215 | I17: =IF(C17<$D$3*G17,"SMALL BASE","ok") -> ok
A19: Read it like this: Central 2015 shows the biggest % by far, but its dollar gain is smaller than several "boring" region-years - the base (2014 profit) was almost zero.

Sheet Charts
A1: Charts

Sheet SQL_vs_Excel
A1: Cross-check: SQL output vs Excel formulas
A2: Blue = pasted from the SQL query Q1 result (regional_growth_analysis.sql). Black = pulled from Growth_Table. Diff should be zero.
A4: Region | B4: Year | C4: SQL Sales | D4: Excel Sales | E4: Diff | F4: SQL Profit | G4: Excel Profit | H4: Diff | I4: Status
A5: Central | B5: 2014 | C5: 103838.16 | D5: =INDEX(Growth_Table!$B$5:$E$8,MATCH($A5,Growth_Table!$A$5:$A$8,0),MATCH($B5,Growth_Table!$B$4:$E$4,0)) -> 103838.16 | E5: =ROUND(D5-C5,2) -> 0 | F5: 539.55 | G5: =INDEX(Growth_Table!$B$21:$E$24,MATCH($A5,Growth_Table!$A$21:$A$24,0),MATCH($B5,Growth_Table!$B$20:$E$20,0)) -> 539.5534 | H5: =ROUND(G5-F5,2) -> 0 | I5: =IF(AND(ABS(E5)<0.01,ABS(H5)<0.01),"Match","CHECK") -> Match
A6: Central | B6: 2015 | C6: 102874.22 | D6: =INDEX(Growth_Table!$B$5:$E$8,MATCH($A6,Growth_Table!$A$5:$A$8,0),MATCH($B6,Growth_Table!$B$4:$E$4,0)) -> 102874.22 | E6: =ROUND(D6-C6,2) -> 0 | F6: 11716.8 | G6: =INDEX(Growth_Table!$B$21:$E$24,MATCH($A6,Growth_Table!$A$21:$A$24,0),MATCH($B6,Growth_Table!$B$20:$E$20,0)) -> 11716.802 | H6: =ROUND(G6-F6,2) -> 0 | I6: =IF(AND(ABS(E6)<0.01,ABS(H6)<0.01),"Match","CHECK") -> Match
A7: Central | B7: 2016 | C7: 147429.38 | D7: =INDEX(Growth_Table!$B$5:$E$8,MATCH($A7,Growth_Table!$A$5:$A$8,0),MATCH($B7,Growth_Table!$B$4:$E$4,0)) -> 147429.38 | E7: =ROUND(D7-C7,2) -> 0 | F7: 19899.16 | G7: =INDEX(Growth_Table!$B$21:$E$24,MATCH($A7,Growth_Table!$A$21:$A$24,0),MATCH($B7,Growth_Table!$B$20:$E$20,0)) -> 19899.163 | H7: =ROUND(G7-F7,2) -> 0 | I7: =IF(AND(ABS(E7)<0.01,ABS(H7)<0.01),"Match","CHECK") -> Match
A8: Central | B8: 2017 | C8: 147098.13 | D8: =INDEX(Growth_Table!$B$5:$E$8,MATCH($A8,Growth_Table!$A$5:$A$8,0),MATCH($B8,Growth_Table!$B$4:$E$4,0)) -> 147098.13 | E8: =ROUND(D8-C8,2) -> 0 | F8: 7550.84 | G8: =INDEX(Growth_Table!$B$21:$E$24,MATCH($A8,Growth_Table!$A$21:$A$24,0),MATCH($B8,Growth_Table!$B$20:$E$20,0)) -> 7550.8442 | H8: =ROUND(G8-F8,2) -> 0 | I8: =IF(AND(ABS(E8)<0.01,ABS(H8)<0.01),"Match","CHECK") -> Match
A9: East | B9: 2014 | C9: 128680.46 | D9: =INDEX(Growth_Table!$B$5:$E$8,MATCH($A9,Growth_Table!$A$5:$A$8,0),MATCH($B9,Growth_Table!$B$4:$E$4,0)) -> 128680.46 | E9: =ROUND(D9-C9,2) -> 0 | F9: 17059.61 | G9: =INDEX(Growth_Table!$B$21:$E$24,MATCH($A9,Growth_Table!$A$21:$A$24,0),MATCH($B9,Growth_Table!$B$20:$E$20,0)) -> 17059.609 | H9: =ROUND(G9-F9,2) -> 0 | I9: =IF(AND(ABS(E9)<0.01,ABS(H9)<0.01),"Match","CHECK") -> Match
A10: East | B10: 2015 | C10: 156332.06 | D10: =INDEX(Growth_Table!$B$5:$E$8,MATCH($A10,Growth_Table!$A$5:$A$8,0),MATCH($B10,Growth_Table!$B$4:$E$4,0)) -> 156332.06 | E10: =ROUND(D10-C10,2) -> 0 | F10: 21091.01 | G10: =INDEX(Growth_Table!$B$21:$E$24,MATCH($A10,Growth_Table!$A$21:$A$24,0),MATCH($B10,Growth_Table!$B$20:$E$20,0)) -> 21091.013 | H10: =ROUND(G10-F10,2) -> 0 | I10: =IF(AND(ABS(E10)<0.01,ABS(H10)<0.01),"Match","CHECK") -> Match
A11: East | B11: 2016 | C11: 180685.82 | D11: =INDEX(Growth_Table!$B$5:$E$8,MATCH($A11,Growth_Table!$A$5:$A$8,0),MATCH($B11,Growth_Table!$B$4:$E$4,0)) -> 180685.82 | E11: =ROUND(D11-C11,2) -> 0 | F11: 20141.6 | G11: =INDEX(Growth_Table!$B$21:$E$24,MATCH($A11,Growth_Table!$A$21:$A$24,0),MATCH($B11,Growth_Table!$B$20:$E$20,0)) -> 20141.596 | H11: =ROUND(G11-F11,2) -> 0 | I11: =IF(AND(ABS(E11)<0.01,ABS(H11)<0.01),"Match","CHECK") -> Match
A12: East | B12: 2017 | C12: 213082.9 | D12: =INDEX(Growth_Table!$B$5:$E$8,MATCH($A12,Growth_Table!$A$5:$A$8,0),MATCH($B12,Growth_Table!$B$4:$E$4,0)) -> 213082.9 | E12: =ROUND(D12-C12,2) -> 0 | F12: 33230.56 | G12: =INDEX(Growth_Table!$B$21:$E$24,MATCH($A12,Growth_Table!$A$21:$A$24,0),MATCH($B12,Growth_Table!$B$20:$E$20,0)) -> 33230.561 | H12: =ROUND(G12-F12,2) -> 0 | I12: =IF(AND(ABS(E12)<0.01,ABS(H12)<0.01),"Match","CHECK") -> Match
A13: South | B13: 2014 | C13: 103845.84 | D13: =INDEX(Growth_Table!$B$5:$E$8,MATCH($A13,Growth_Table!$A$5:$A$8,0),MATCH($B13,Growth_Table!$B$4:$E$4,0)) -> 103845.84 | E13: =ROUND(D13-C13,2) -> 0 | F13: 11879.12 | G13: =INDEX(Growth_Table!$B$21:$E$24,MATCH($A13,Growth_Table!$A$21:$A$24,0),MATCH($B13,Growth_Table!$B$20:$E$20,0)) -> 11879.12 | H13: =ROUND(G13-F13,2) -> 0 | I13: =IF(AND(ABS(E13)<0.01,ABS(H13)<0.01),"Match","CHECK") -> Match
A14: South | B14: 2015 | C14: 71359.98 | D14: =INDEX(Growth_Table!$B$5:$E$8,MATCH($A14,Growth_Table!$A$5:$A$8,0),MATCH($B14,Growth_Table!$B$4:$E$4,0)) -> 71359.981 | E14: =ROUND(D14-C14,2) -> 0 | F14: 8318.59 | G14: =INDEX(Growth_Table!$B$21:$E$24,MATCH($A14,Growth_Table!$A$21:$A$24,0),MATCH($B14,Growth_Table!$B$20:$E$20,0)) -> 8318.594 | H14: =ROUND(G14-F14,2) -> 0 | I14: =IF(AND(ABS(E14)<0.01,ABS(H14)<0.01),"Match","CHECK") -> Match
A15: South | B15: 2016 | C15: 93610.22 | D15: =INDEX(Growth_Table!$B$5:$E$8,MATCH($A15,Growth_Table!$A$5:$A$8,0),MATCH($B15,Growth_Table!$B$4:$E$4,0)) -> 93610.223 | E15: =ROUND(D15-C15,2) -> 0 | F15: 17702.81 | G15: =INDEX(Growth_Table!$B$21:$E$24,MATCH($A15,Growth_Table!$A$21:$A$24,0),MATCH($B15,Growth_Table!$B$20:$E$20,0)) -> 17702.808 | H15: =ROUND(G15-F15,2) -> 0 | I15: =IF(AND(ABS(E15)<0.01,ABS(H15)<0.01),"Match","CHECK") -> Match
A16: South | B16: 2017 | C16: 122905.86 | D16: =INDEX(Growth_Table!$B$5:$E$8,MATCH($A16,Growth_Table!$A$5:$A$8,0),MATCH($B16,Growth_Table!$B$4:$E$4,0)) -> 122905.86 | E16: =ROUND(D16-C16,2) -> 0 | F16: 8848.91 | G16: =INDEX(Growth_Table!$B$21:$E$24,MATCH($A16,Growth_Table!$A$21:$A$24,0),MATCH($B16,Growth_Table!$B$20:$E$20,0)) -> 8848.9079 | H16: =ROUND(G16-F16,2) -> 0 | I16: =IF(AND(ABS(E16)<0.01,ABS(H16)<0.01),"Match","CHECK") -> Match
... A20: West | B20: 2017 | C20: 250128.37 | D20: =INDEX(Growth_Table!$B$5:$E$8,MATCH($A20,Growth_Table!$A$5:$A$8,0),MATCH($B20,Growth_Table!$B$4:$E$4,0)) -> 250128.37 | E20: =ROUND(D20-C20,2) -> 0 | F20: 43808.96 | G20: =INDEX(Growth_Table!$B$21:$E$24,MATCH($A20,Growth_Table!$A$21:$A$24,0),MATCH($B20,Growth_Table!$B$20:$E$20,0)) -> 43808.956 | H20: =ROUND(G20-F20,2) -> 0 | I20: =IF(AND(ABS(E20)<0.01,ABS(H20)<0.01),"Match","CHECK") -> Match
A22: Rows matching | C22: =COUNTIF(I5:I20,"Match")&" of "&COUNTA(I5:I20) -> 16 of 16

Sheet Insights
A1: Five Insights
A3: Insight | B3: What the data shows | C3: So what / action
A4: 1. West and East carry the growth | B4: West (CAGR 19.1%) and East (18.3%) together added about 75% of the company's $249k sales gain between 2014 and 2017. East grew in every single year (+21.5%, +15.6%, +17.9%); West dipped 5.4% in 2015 and then jumped 34% and 33%. | C4: Plan growth targets and stock around these two; East is the more predictable one.
A5: 2. South's swings are partly one big order | B5: One Cisco TelePresence order of $22,638 (March 2014) was 21.8% of South's 2014 sales. Without it the 2014 base is about $81.2k and the 2015 drop is -12.1%, not -31.3%. Even after two +31% years, South's CAGR is only 5.8%, the lowest of all regions. | C5: Check for one-off orders before quoting a growth rate; consider reporting with and without outliers.
A6: 3. Central's +2,072% profit growth is a small-base effect | B6: Central earned just $540 in 2014 (0.5% margin). Going to $11,717 in 2015 is +2,072%, but the dollar gain ($11.2k) is smaller than East's 2017 gain of $13.1k, which was only +65%. | C6: Always show absolute change next to the percentage; flag any base below the region's normal level.
A7: 4. Central is growing sales but losing the profit | B7: Central 2017 sales were flat (-0.2%) while profit fell 62% to $7.6k and margin dropped from 13.5% to 5.1%. Central gives the highest average discount (22-27% vs 10-16% in West/East), and Texas and Illinois together lost about $15.6k in 2017. Without those two states Central would have made roughly $23k. | C7: Review discount policy and the product mix sold in Texas and Illinois.
A8: 5. Compare the same quarter, not the previous quarter | B8: Every region peaks in Q4. Central went from $33.4k in Q3-2016 to $68.1k in Q4-2016 (+104%) - but versus Q4-2015 the real growth was +59.7%. Sequential growth mixes seasonality with growth. | C8: Use same-quarter-last-year (or full-year) comparisons for fair period-over-period analysis.
